day2/ex2/codinger_83.v
module codinger_83(
    output reg [2:0] y,
    input[7:0] i,
    output reg v
);
    always @(*) begin
       if(i == 8'b00000000)
            begin
                v=0;
                y=3'b000;
            end
        else if(i[7]==1)
            begin
                v=1;
                y=3'b111;
            end
        else if(i[6]==1)
            begin
                v=1;
                y=3'b110;
            end
        else if(i[5]==1)
            begin
                v=1;
                y=3'b101;
            end
        else if(i[4]==1)
            begin
                v=1;
                y=3'b100;
            end
        else if(i[3]==1)
            begin
                v=1;
                y=3'b011;
            end
        else if(i[2]==1)
            begin
                v=1;
                y=3'b010;
            end 
        else if(i[1]==1)
            begin
                v=1;
                y=3'b001;
            end  
        else if(i[0]==1)
            begin
                v=1;
                y=3'b000;
            end
    end



endmodule

day2/ex2/codinger_tb.v
module codinger_tb();
    reg[7:0] i;
    wire v;
    wire [2:0] y;
    integer k;

    codinger_83 uut(
    .i(i),
    .y(y),
    .v(v)
);

    initial begin
        $dumpfile("wave.vcd");
        $dumpvars(0, codinger_tb);
        
        i=8'b00000000; #10;
        for(k=0;k<=256;k=k+1)begin
                i=k;
                #5;
        end
        $finish;
    end
endmodule

day2/ex2/wave.vcd
$date
	Tue Jul 07 10:17:19 2026
$end
$version
	Icarus Verilog
$end
$timescale
	1s
$end
$scope module codinger_tb $end
$var wire 3 ! y [2:0] $end
$var wire 1 " v $end
$var reg 8 # i [7:0] $end
$var integer 32 $ k [31:0] $end
$scope module uut $end
$var wire 8 % i [7:0] $end
$var reg 1 " v $end
$var reg 3 & y [2:0] $end
$upscope $end
$upscope $end
$enddefinitions $end
$comment Show the parameter values. $end
$dumpall
$end
#0
$dumpvars
b0 &
b0 %
bx $
b0 #
0"
b0 !
$end
#10
b0 $
#15
1"
b1 #
b1 %
b1 $
#20
b1 !
b1 &
b10 #
b10 %
b10 $
#25
b11 #
b11 %
b11 $
#30
b10 !
b10 &
b100 #
b100 %
b100 $
#35
b101 #
b101 %
b101 $
#40
b110 #
b110 %
b110 $
#45
b111 #
b111 %
b111 $
#50
b11 !
b11 &
b1000 #
b1000 %
b1000 $
#55
b1001 #
b1001 %
b1001 $
#60
b1010 #
b1010 %
b1010 $
#65
b1011 #
b1011 %
b1011 $
#70
b1100 #
b1100 %
b1100 $
#75
b1101 #
b1101 %
b1101 $
#80
b1110 #
b1110 %
b1110 $
#85
b1111 #
b1111 %
b1111 $
#90
b100 !
b100 &
b10000 #
b10000 %
b10000 $
#95
b10001 #
b10001 %
b10001 $
#100
b10010 #
b10010 %
b10010 $
#105
b10011 #
b10011 %
b10011 $
#110
b10100 #
b10100 %
b10100 $
#115
b10101 #
b10101 %
b10101 $
#120
b10110 #
b10110 %
b10110 $
#125
b10111 #
b10111 %
b10111 $
#130
b11000 #
b11000 %
b11000 $
#135
b11001 #
b11001 %
b11001 $
#140
b11010 #
b11010 %
b11010 $
#145
b11011 #
b11011 %
b11011 $
#150
b11100 #
b11100 %
b11100 $
#155
b11101 #
b11101 %
b11101 $
#160
b11110 #
b11110 %
b11110 $
#165
b11111 #
b11111 %
b11111 $
#170
b101 !
b101 &
b100000 #
b100000 %
b100000 $
#175
b100001 #
b100001 %
b100001 $
#180
b100010 #
b100010 %
b100010 $
#185
b100011 #
b100011 %
b100011 $
#190
b100100 #
b100100 %
b100100 $
#195
b100101 #
b100101 %
b100101 $
#200
b100110 #
b100110 %
b100110 $
#205
b100111 #
b100111 %
b100111 $
#210
b101000 #
b101000 %
b101000 $
#215
b101001 #
b101001 %
b101001 $
#220
b101010 #
b101010 %
b101010 $
#225
b101011 #
b101011 %
b101011 $
#230
b101100 #
b101100 %
b101100 $
#235
b101101 #
b101101 %
b101101 $
#240
b101110 #
b101110 %
b101110 $
#245
b101111 #
b101111 %
b101111 $
#250
b110000 #
b110000 %
b110000 $
#255
b110001 #
b110001 %
b110001 $
#260
b110010 #
b110010 %
b110010 $
#265
b110011 #
b110011 %
b110011 $
#270
b110100 #
b110100 %
b110100 $
#275
b110101 #
b110101 %
b110101 $
#280
b110110 #
b110110 %
b110110 $
#285
b110111 #
b110111 %
b110111 $
#290
b111000 #
b111000 %
b111000 $
#295
b111001 #
b111001 %
b111001 $
#300
b111010 #
b111010 %
b111010 $
#305
b111011 #
b111011 %
b111011 $
#310
b111100 #
b111100 %
b111100 $
#315
b111101 #
b111101 %
b111101 $
#320
b111110 #
b111110 %
b111110 $
#325
b111111 #
b111111 %
b111111 $
#330
b110 !
b110 &
b1000000 #
b1000000 %
b1000000 $
#335
b1000001 #
b1000001 %
b1000001 $
#340
b1000010 #
b1000010 %
b1000010 $
#345
b1000011 #
b1000011 %
b1000011 $
#350
b1000100 #
b1000100 %
b1000100 $
#355
b1000101 #
b1000101 %
b1000101 $
#360
b1000110 #
b1000110 %
b1000110 $
#365
b1000111 #
b1000111 %
b1000111 $
#370
b1001000 #
b1001000 %
b1001000 $
#375
b1001001 #
b1001001 %
b1001001 $
#380
b1001010 #
b1001010 %
b1001010 $
#385
b1001011 #
b1001011 %
b1001011 $
#390
b1001100 #
b1001100 %
b1001100 $
#395
b1001101 #
b1001101 %
b1001101 $
#400
b1001110 #
b1001110 %
b1001110 $
#405
b1001111 #
b1001111 %
b1001111 $
#410
b1010000 #
b1010000 %
b1010000 $
#415
b1010001 #
b1010001 %
b1010001 $
#420
b1010010 #
b1010010 %
b1010010 $
#425
b1010011 #
b1010011 %
b1010011 $
#430
b1010100 #
b1010100 %
b1010100 $
#435
b1010101 #
b1010101 %
b1010101 $
#440
b1010110 #
b1010110 %
b1010110 $
#445
b1010111 #
b1010111 %
b1010111 $
#450
b1011000 #
b1011000 %
b1011000 $
#455
b1011001 #
b1011001 %
b1011001 $
#460
b1011010 #
b1011010 %
b1011010 $
#465
b1011011 #
b1011011 %
b1011011 $
#470
b1011100 #
b1011100 %
b1011100 $
#475
b1011101 #
b1011101 %
b1011101 $
#480
b1011110 #
b1011110 %
b1011110 $
#485
b1011111 #
b1011111 %
b1011111 $
#490
b1100000 #
b1100000 %
b1100000 $
#495
b1100001 #
b1100001 %
b1100001 $
#500
b1100010 #
b1100010 %
b1100010 $
#505
b1100011 #
b1100011 %
b1100011 $
#510
b1100100 #
b1100100 %
b1100100 $
#515
b1100101 #
b1100101 %
b1100101 $
#520
b1100110 #
b1100110 %
b1100110 $
#525
b1100111 #
b1100111 %
b1100111 $
#530
b1101000 #
b1101000 %
b1101000 $
#535
b1101001 #
b1101001 %
b1101001 $
#540
b1101010 #
b1101010 %
b1101010 $
#545
b1101011 #
b1101011 %
b1101011 $
#550
b1101100 #
b1101100 %
b1101100 $
#555
b1101101 #
b1101101 %
b1101101 $
#560
b1101110 #
b1101110 %
b1101110 $
#565
b1101111 #
b1101111 %
b1101111 $
#570
b1110000 #
b1110000 %
b1110000 $
#575
b1110001 #
b1110001 %
b1110001 $
#580
b1110010 #
b1110010 %
b1110010 $
#585
b1110011 #
b1110011 %
b1110011 $
#590
b1110100 #
b1110100 %
b1110100 $
#595
b1110101 #
b1110101 %
b1110101 $
#600
b1110110 #
b1110110 %
b1110110 $
#605
b1110111 #
b1110111 %
b1110111 $
#610
b1111000 #
b1111000 %
b1111000 $
#615
b1111001 #
b1111001 %
b1111001 $
#620
b1111010 #
b1111010 %
b1111010 $
#625
b1111011 #
b1111011 %
b1111011 $
#630
b1111100 #
b1111100 %
b1111100 $
#635
b1111101 #
b1111101 %
b1111101 $
#640
b1111110 #
b1111110 %
b1111110 $
#645
b1111111 #
b1111111 %
b1111111 $
#650
b111 !
b111 &
b10000000 #
b10000000 %
b10000000 $
#655
b10000001 #
b10000001 %
b10000001 $
#660
b10000010 #
b10000010 %
b10000010 $
#665
b10000011 #
b10000011 %
b10000011 $
#670
b10000100 #
b10000100 %
b10000100 $
#675
b10000101 #
b10000101 %
b10000101 $
#680
b10000110 #
b10000110 %
b10000110 $
#685
b10000111 #
b10000111 %
b10000111 $
#690
b10001000 #
b10001000 %
b10001000 $
#695
b10001001 #
b10001001 %
b10001001 $
#700
b10001010 #
b10001010 %
b10001010 $
#705
b10001011 #
b10001011 %
b10001011 $
#710
b10001100 #
b10001100 %
b10001100 $
#715
b10001101 #
b10001101 %
b10001101 $
#720
b10001110 #
b10001110 %
b10001110 $
#725
b10001111 #
b10001111 %
b10001111 $
#730
b10010000 #
b10010000 %
b10010000 $
#735
b10010001 #
b10010001 %
b10010001 $
#740
b10010010 #
b10010010 %
b10010010 $
#745
b10010011 #
b10010011 %
b10010011 $
#750
b10010100 #
b10010100 %
b10010100 $
#755
b10010101 #
b10010101 %
b10010101 $
#760
b10010110 #
b10010110 %
b10010110 $
#765
b10010111 #
b10010111 %
b10010111 $
#770
b10011000 #
b10011000 %
b10011000 $
#775
b10011001 #
b10011001 %
b10011001 $
#780
b10011010 #
b10011010 %
b10011010 $
#785
b10011011 #
b10011011 %
b10011011 $
#790
b10011100 #
b10011100 %
b10011100 $
#795
b10011101 #
b10011101 %
b10011101 $
#800
b10011110 #
b10011110 %
b10011110 $
#805
b10011111 #
b10011111 %
b10011111 $
#810
b10100000 #
b10100000 %
b10100000 $
#815
b10100001 #
b10100001 %
b10100001 $
#820
b10100010 #
b10100010 %
b10100010 $
#825
b10100011 #
b10100011 %
b10100011 $
#830
b10100100 #
b10100100 %
b10100100 $
#835
b10100101 #
b10100101 %
b10100101 $
#840
b10100110 #
b10100110 %
b10100110 $
#845
b10100111 #
b10100111 %
b10100111 $
#850
b10101000 #
b10101000 %
b10101000 $
#855
b10101001 #
b10101001 %
b10101001 $
#860
b10101010 #
b10101010 %
b10101010 $
#865
b10101011 #
b10101011 %
b10101011 $
#870
b10101100 #
b10101100 %
b10101100 $
#875
b10101101 #
b10101101 %
b10101101 $
#880
b10101110 #
b10101110 %
b10101110 $
#885
b10101111 #
b10101111 %
b10101111 $
#890
b10110000 #
b10110000 %
b10110000 $
#895
b10110001 #
b10110001 %
b10110001 $
#900
b10110010 #
b10110010 %
b10110010 $
#905
b10110011 #
b10110011 %
b10110011 $
#910
b10110100 #
b10110100 %
b10110100 $
#915
b10110101 #
b10110101 %
b10110101 $
#920
b10110110 #
b10110110 %
b10110110 $
#925
b10110111 #
b10110111 %
b10110111 $
#930
b10111000 #
b10111000 %
b10111000 $
#935
b10111001 #
b10111001 %
b10111001 $
#940
b10111010 #
b10111010 %
b10111010 $
#945
b10111011 #
b10111011 %
b10111011 $
#950
b10111100 #
b10111100 %
b10111100 $
#955
b10111101 #
b10111101 %
b10111101 $
#960
b10111110 #
b10111110 %
b10111110 $
#965
b10111111 #
b10111111 %
b10111111 $
#970
b11000000 #
b11000000 %
b11000000 $
#975
b11000001 #
b11000001 %
b11000001 $
#980
b11000010 #
b11000010 %
b11000010 $
#985
b11000011 #
b11000011 %
b11000011 $
#990
b11000100 #
b11000100 %
b11000100 $
#995
b11000101 #
b11000101 %
b11000101 $
#1000
b11000110 #
b11000110 %
b11000110 $
#1005
b11000111 #
b11000111 %
b11000111 $
#1010
b11001000 #
b11001000 %
b11001000 $
#1015
b11001001 #
b11001001 %
b11001001 $
#1020
b11001010 #
b11001010 %
b11001010 $
#1025
b11001011 #
b11001011 %
b11001011 $
#1030
b11001100 #
b11001100 %
b11001100 $
#1035
b11001101 #
b11001101 %
b11001101 $
#1040
b11001110 #
b11001110 %
b11001110 $
#1045
b11001111 #
b11001111 %
b11001111 $
#1050
b11010000 #
b11010000 %
b11010000 $
#1055
b11010001 #
b11010001 %
b11010001 $
#1060
b11010010 #
b11010010 %
b11010010 $
#1065
b11010011 #
b11010011 %
b11010011 $
#1070
b11010100 #
b11010100 %
b11010100 $
#1075
b11010101 #
b11010101 %
b11010101 $
#1080
b11010110 #
b11010110 %
b11010110 $
#1085
b11010111 #
b11010111 %
b11010111 $
#1090
b11011000 #
b11011000 %
b11011000 $
#1095
b11011001 #
b11011001 %
b11011001 $
#1100
b11011010 #
b11011010 %
b11011010 $
#1105
b11011011 #
b11011011 %
b11011011 $
#1110
b11011100 #
b11011100 %
b11011100 $
#1115
b11011101 #
b11011101 %
b11011101 $
#1120
b11011110 #
b11011110 %
b11011110 $
#1125
b11011111 #
b11011111 %
b11011111 $
#1130
b11100000 #
b11100000 %
b11100000 $
#1135
b11100001 #
b11100001 %
b11100001 $
#1140
b11100010 #
b11100010 %
b11100010 $
#1145
b11100011 #
b11100011 %
b11100011 $
#1150
b11100100 #
b11100100 %
b11100100 $
#1155
b11100101 #
b11100101 %
b11100101 $
#1160
b11100110 #
b11100110 %
b11100110 $
#1165
b11100111 #
b11100111 %
b11100111 $
#1170
b11101000 #
b11101000 %
b11101000 $
#1175
b11101001 #
b11101001 %
b11101001 $
#1180
b11101010 #
b11101010 %
b11101010 $
#1185
b11101011 #
b11101011 %
b11101011 $
#1190
b11101100 #
b11101100 %
b11101100 $
#1195
b11101101 #
b11101101 %
b11101101 $
#1200
b11101110 #
b11101110 %
b11101110 $
#1205
b11101111 #
b11101111 %
b11101111 $
#1210
b11110000 #
b11110000 %
b11110000 $
#1215
b11110001 #
b11110001 %
b11110001 $
#1220
b11110010 #
b11110010 %
b11110010 $
#1225
b11110011 #
b11110011 %
b11110011 $
#1230
b11110100 #
b11110100 %
b11110100 $
#1235
b11110101 #
b11110101 %
b11110101 $
#1240
b11110110 #
b11110110 %
b11110110 $
#1245
b11110111 #
b11110111 %
b11110111 $
#1250
b11111000 #
b11111000 %
b11111000 $
#1255
b11111001 #
b11111001 %
b11111001 $
#1260
b11111010 #
b11111010 %
b11111010 $
#1265
b11111011 #
b11111011 %
b11111011 $
#1270
b11111100 #
b11111100 %
b11111100 $
#1275
b11111101 #
b11111101 %
b11111101 $
#1280
b11111110 #
b11111110 %
b11111110 $
#1285
b11111111 #
b11111111 %
b11111111 $
#1290
b0 !
b0 &
0"
b0 #
b0 %
b100000000 $
#1295
b100000001 $
